mcp_protocol_bridge.py
mcp_protocol_bridge-0.3.1.dist-info/METADATA
mcp_protocol_bridge-0.3.1.dist-info/WHEEL
mcp_protocol_bridge-0.3.1.dist-info/entry_points.txt
mcp_protocol_bridge-0.3.1.dist-info/RECORD
